pykeafortune/__init__.py
pykeafortune/__main__.py
pykeafortune/fortune_cookie.py
pykeafortune/horoscope.py
pykeafortune/lucky_day.py
pykeafortune/lucky_number.py
pykeafortune-1.0.0.dist-info/licenses/LICENSE
pykeafortune-1.0.0.dist-info/METADATA
pykeafortune-1.0.0.dist-info/WHEEL
pykeafortune-1.0.0.dist-info/top_level.txt
pykeafortune-1.0.0.dist-info/RECORD
