Metadata-Version: 2.4
Name: pykeafortune
Version: 1.0.0
Summary: A Python package for generating horoscopes, fortunes, and lucky numbers.
Author-email: James Hou <jjh9584@nyu.edu>, Maya Felix <Mxf4596@nyu.edu>, Larry Yang <ly2380@nyu.edu>, Matthew Cheng <mc9283@nyu.edu>
License:                     GNU GENERAL PUBLIC LICENSE
Project-URL: Homepage, https://github.com/software-students-spring2025/3-python-package-pyke-ult
Keywords: horoscope,fortune,lucky,numbers,generation,fun
Requires-Python: >=3.11
License-File: LICENSE
Dynamic: license-file
